pydantic_ai_todo/__init__.py
pydantic_ai_todo/py.typed
pydantic_ai_todo/storage.py
pydantic_ai_todo/toolset.py
pydantic_ai_todo/types.py
pydantic_ai_todo-0.1.1.dist-info/METADATA
pydantic_ai_todo-0.1.1.dist-info/WHEEL
pydantic_ai_todo-0.1.1.dist-info/licenses/LICENSE
pydantic_ai_todo-0.1.1.dist-info/RECORD
