Metadata-Version: 2.4
Name: pydantic-ai-todo
Version: 0.1.1
Summary: Todo/task planning toolset for pydantic-ai agents
Project-URL: Homepage, https://github.com/vstorm-co/pydantic-ai-todo
Project-URL: Documentation, https://github.com/vstorm-co/pydantic-ai-todo#readme
Project-URL: Repository, https://github.com/vstorm-co/pydantic-ai-todo
Project-URL: Issues, https://github.com/vstorm-co/pydantic-ai-todo/issues
Project-URL: Changelog, https://github.com/vstorm-co/pydantic-ai-todo/releases
Author-email: VStorm <hello@vstorm.co>
License: MIT License
License-File: LICENSE
Keywords: agents,ai,pydantic,pydantic-ai,task-management,todo,toolset
Classifier: Development Status :: 4 - Beta
Classifier: Intended Audience :: Developers
Classifier: License :: OSI Approved :: MIT License
Classifier: Programming Language :: Python :: 3
Classifier: Programming Language :: Python :: 3.10
Classifier: Programming Language :: Python :: 3.11
Classifier: Programming Language :: Python :: 3.12
Classifier: Programming Language :: Python :: 3.13
Classifier: Topic :: Scientific/Engineering :: Artificial Intelligence
Classifier: Topic :: Software Development :: Libraries :: Python Modules
Classifier: Typing :: Typed
Requires-Python: >=3.10
Requires-Dist: pydantic-ai>=0.1.0
Requires-Dist: pydantic>=2.0
